nightHua/Config.py
nightHua/Usual.py
nightHua/__init__.py
nightHua-1.1.2.dist-info/LICENSE
nightHua-1.1.2.dist-info/METADATA
nightHua-1.1.2.dist-info/WHEEL
nightHua-1.1.2.dist-info/top_level.txt
nightHua-1.1.2.dist-info/RECORD
