Metadata-Version: 2.1
Name: nightHua
Version: 1.1.2
Summary: 自用模块
Author: nightHua
Author-email: lirui001002@163.com
License: UNKNOWN
Platform: UNKNOWN
Classifier: Programming Language :: Python :: 3
Classifier: License :: OSI Approved :: MIT License
Classifier: Operating System :: OS Independent
Requires-Python: >=3.6
License-File: LICENSE
